.VERSION
AUTHORS.rst
CONTRIBUTING.rst
HISTORY.rst
LICENSE
MANIFEST.in
Pipfile
Pipfile.lock
README.rst
USAGE.rst
dev-requirements.txt
requirements.txt
setup.cfg
setup.py
docs/Makefile
docs/authors.rst
docs/conf.py
docs/contributing.rst
docs/history.rst
docs/index.rst
docs/installation.rst
docs/readme.rst
docs/usage.rst
ynablib/.VERSION
ynablib/AUTHORS.rst
ynablib/CONTRIBUTING.rst
ynablib/HISTORY.rst
ynablib/LICENSE
ynablib/Pipfile
ynablib/Pipfile.lock
ynablib/README.rst
ynablib/USAGE.rst
ynablib/__init__.py
ynablib/_version.py
ynablib/dev-requirements.txt
ynablib/requirements.txt
ynablib/ynablib.py
ynablib/ynablibexceptions.py
ynablib.egg-info/PKG-INFO
ynablib.egg-info/SOURCES.txt
ynablib.egg-info/dependency_links.txt
ynablib.egg-info/not-zip-safe
ynablib.egg-info/requires.txt
ynablib.egg-info/top_level.txt
ynablib/__pycache__/__init__.cpython-37.pyc
ynablib/__pycache__/_version.cpython-37.pyc
ynablib/__pycache__/ynablib.cpython-37.pyc
ynablib/__pycache__/ynablibexceptions.cpython-37.pyc