Metadata-Version: 1.1
Name: ynablib
Version: 0.2.0
Summary: A library implementing basic interaction with the YNAB service
Home-page: https://github.com/costastf/ynablib
Author: Costas Tyfoxylos
Author-email: costas.tyf@gmail.com
License: MIT
Keywords: ynablib ynab python
Platform: UNKNOWN
Classifier: Development Status :: 4 - Beta
Classifier: Intended Audience :: Developers
Classifier: License :: OSI Approved :: MIT License
Classifier: Natural Language :: English
Classifier: Programming Language :: Python :: 3.7
